sbomac/__init__.py
sbomac/cli.py
sbomac/parse.py
sbomac/scanner.py
sbomac/version.py
sbomac-0.1.0.dist-info/licenses/LICENSE
sbomac-0.1.0.dist-info/METADATA
sbomac-0.1.0.dist-info/WHEEL
sbomac-0.1.0.dist-info/entry_points.txt
sbomac-0.1.0.dist-info/top_level.txt
sbomac-0.1.0.dist-info/RECORD
